red_pandas.py
setup.py
red_pandas.egg-info/PKG-INFO
red_pandas.egg-info/SOURCES.txt
red_pandas.egg-info/dependency_links.txt
red_pandas.egg-info/entry_points.txt
red_pandas.egg-info/requires.txt
red_pandas.egg-info/top_level.txt
utils/__init__.py
utils/pandas_utils.py