Metadata-Version: 1.2
Name: red-pandas
Version: 0.6
Summary: A random test lib
Home-page: UNKNOWN
Author: UNKNOWN
Author-email: UNKNOWN
License: UNKNOWN
Platform: UNKNOWN
Requires-Python: <3.0.*
